MANIFEST.in
README.markdown
setup.py
cropper_img/__init__.py
cropper_img/comix_img.py
cropper_img.egg-info/PKG-INFO
cropper_img.egg-info/SOURCES.txt
cropper_img.egg-info/dependency_links.txt
cropper_img.egg-info/entry_points.txt
cropper_img.egg-info/not-zip-safe
cropper_img.egg-info/top_level.txt