Metadata-Version: 1.1
Name: cropper-img
Version: 0.1.4
Summary: image splitting
Home-page: UNKNOWN
Author: andry1983
Author-email: andry1983g28@gmail.com
License: UNKNOWN
Keywords: images
Platform: UNKNOWN
Classifier: Environment :: Web Environment
Classifier: Intended Audience :: Developers
Classifier: Programming Language :: Python
Requires: python (>= 3.0)
Requires: Pillow (>=5.0)
